hack4uTerror/__init__.py
hack4uTerror/courses.py
hack4uTerror/utils.py
hack4uTerror-0.1.1.dist-info/METADATA
hack4uTerror-0.1.1.dist-info/WHEEL
hack4uTerror-0.1.1.dist-info/top_level.txt
hack4uTerror-0.1.1.dist-info/RECORD
